dhl/__init__.py
dhl/service.py
dhl/resources/__init__.py
dhl/resources/address.py
dhl/resources/package.py
dhl/resources/response.py
dhl/resources/shipment.py
python_dhl-1.0.0.dev14.dist-info/DESCRIPTION.rst
python_dhl-1.0.0.dev14.dist-info/METADATA
python_dhl-1.0.0.dev14.dist-info/metadata.json
python_dhl-1.0.0.dev14.dist-info/pbr.json
python_dhl-1.0.0.dev14.dist-info/RECORD
python_dhl-1.0.0.dev14.dist-info/top_level.txt
python_dhl-1.0.0.dev14.dist-info/WHEEL
