Metadata-Version: 1.1
Name: python-dhl
Version: 1.0.0.dev14
Summary: Python package for DHL webservice
Home-page: https://github.com/benqo/python-dhl
Author: Benjamin Polovic
Author-email: benkoman@gmail.com
License: MIT
Platform: UNKNOWN
Classifier: Development Status :: 3 - Alpha
Classifier: Intended Audience :: Developers
Classifier: License :: OSI Approved :: MIT License
Classifier: Programming Language :: Python :: 3.4
